odoo9_addon_medical_physician-9.0.1.0.0.99.dev8-py2.7-nspkg.pth
odoo9_addon_medical_physician-9.0.1.0.0.99.dev8.dist-info/DESCRIPTION.rst
odoo9_addon_medical_physician-9.0.1.0.0.99.dev8.dist-info/METADATA
odoo9_addon_medical_physician-9.0.1.0.0.99.dev8.dist-info/RECORD
odoo9_addon_medical_physician-9.0.1.0.0.99.dev8.dist-info/WHEEL
odoo9_addon_medical_physician-9.0.1.0.0.99.dev8.dist-info/metadata.json
odoo9_addon_medical_physician-9.0.1.0.0.99.dev8.dist-info/namespace_packages.txt
odoo9_addon_medical_physician-9.0.1.0.0.99.dev8.dist-info/top_level.txt
odoo_addons/medical_physician/README.rst
odoo_addons/medical_physician/__init__.py
odoo_addons/medical_physician/__openerp__.py
odoo_addons/medical_physician/data/ir_sequence_data.xml
odoo_addons/medical_physician/data/medical_specialties.xml
odoo_addons/medical_physician/demo/medical_physician_demo.xml
odoo_addons/medical_physician/i18n/es_CO.po
odoo_addons/medical_physician/i18n/es_ES.po
odoo_addons/medical_physician/i18n/pt_BR.po
odoo_addons/medical_physician/i18n/ro.po
odoo_addons/medical_physician/models/__init__.py
odoo_addons/medical_physician/models/medical_physician.py
odoo_addons/medical_physician/models/medical_specialty.py
odoo_addons/medical_physician/security/ir.model.access.csv
odoo_addons/medical_physician/static/description/icon.png
odoo_addons/medical_physician/tests/__init__.py
odoo_addons/medical_physician/tests/test_medical_physician.py
odoo_addons/medical_physician/views/medical_menu.xml
odoo_addons/medical_physician/views/medical_physician_view.xml
odoo_addons/medical_physician/views/medical_specialty_view.xml
